<?xml version="1.0" encoding="utf-8"?>
<odoo>
    <record id="action_report_book_card" model="ir.actions.report">
        <field name="name">Book Card</field>
        <field name="model">library.book</field>
        <field name="report_type">qweb-pdf</field>
        <field name="report_name">my_library.template_book_card</field>
        <field name="report_file">my_library.template_book_card</field>
        <field name="binding_model_id" ref="model_library_book"/>
        <field name="binding_type">report</field>
    </record>
</odoo>